{
    "Genshin Impact": "https://i.ibb.co/Cpyt70G/Genshin-Impact-Logo.png",
    "Kirby": "https://i.ibb.co/jZrfPKy/2560px-Kirby-2022-logo-svg.png",
    "Jujutsu Kaisen": "https://i.ibb.co/8c4XGwp/1200px-Jujutsu-Kaisen-logo.png",
    "Splatoon": "https://i.ibb.co/7nHhNdt/A-Splatoon-logo.png",
    "Super Animal Royale": "https://i.ibb.co/BG1QzCs/4bcc84bfaa3abea4e449107cfb3ee73e.png",
    "Miraculous: Tales of Ladybug & Cat Noir": "https://i.ibb.co/hZFmNCL/Miraculous-Ladybug-Logo.png",
    "Geometry Dash": "https://i.ibb.co/vsQfNt1/Geometry-Dash.png"
}
